apertium/__init__.py
apertium/iso639.py
apertium/mode_search.py
apertium/utils.py
apertium/analysis/__init__.py
apertium/generation/__init__.py
apertium/translation/__init__.py
apertium_app-1.1.dist-info/LICENSE
apertium_app-1.1.dist-info/METADATA
apertium_app-1.1.dist-info/WHEEL
apertium_app-1.1.dist-info/top_level.txt
apertium_app-1.1.dist-info/RECORD
