Metadata-Version: 2.1
Name: apertium-app
Version: 1.1
Summary: this is a python library for apertium
Home-page: https://github.com/apertium/apertium-python/
Author: James Sandy
Author-email: mondaysandy3@gmail.com
License: UNKNOWN
Platform: UNKNOWN
Classifier: Programming Language :: Python :: 3
Classifier: License :: OSI Approved :: MIT License
Classifier: Operating System :: OS Independent
